eloq_sdk/__init__.py
eloq_sdk/__version__.py
eloq_sdk/client.py
eloq_sdk/exceptions.py
eloq_sdk/schema.py
eloq_sdk/utils.py
eloq_sdk-0.1.4.dist-info/METADATA
eloq_sdk-0.1.4.dist-info/WHEEL
eloq_sdk-0.1.4.dist-info/top_level.txt
eloq_sdk-0.1.4.dist-info/RECORD
